experiment_lab/__init__.py
experiment_lab/common/__init__.py
experiment_lab/common/networks/__init__.py
experiment_lab/common/networks/blocks.py
experiment_lab/common/networks/mlp.py
experiment_lab/common/networks/network.py
experiment_lab/common/resolvers/__init__.py
experiment_lab/common/resolvers/list_resolvers.py
experiment_lab/common/resolvers/object_resolvers.py
experiment_lab/common/utils/__init__.py
experiment_lab/configs/config.yaml
experiment_lab/configs/__pycache__/__init__.cpython-311.pyc
experiment_lab/configs/mc/config.yaml
experiment_lab/configs/mc/estimate_pi.yaml
experiment_lab/configs/rl/atari.yaml
experiment_lab/configs/rl/cartpole.yaml
experiment_lab/configs/rl/config.yaml
experiment_lab/configs/rl/crossing.yaml
experiment_lab/configs/rl/walker.yaml
experiment_lab/configs/supervised/config.yaml
experiment_lab/configs/supervised/fashion_mnist.yaml
experiment_lab/core/__init__.py
experiment_lab/core/base_analysis.py
experiment_lab/core/base_config.py
experiment_lab/core/base_experiment.py
experiment_lab/core/runner.py
experiment_lab/experiments/__init__.py
experiment_lab/experiments/examples/__init__.py
experiment_lab/experiments/examples/mc_pi_estimate.py
experiment_lab/experiments/examples/random_waits.py
experiment_lab/experiments/monte_carlo/__init__.py
experiment_lab/experiments/monte_carlo/config.py
experiment_lab/experiments/monte_carlo/experiment.py
experiment_lab/experiments/monte_carlo/main.py
experiment_lab/experiments/monte_carlo/components/__init__.py
experiment_lab/experiments/monte_carlo/components/aggregators.py
experiment_lab/experiments/monte_carlo/components/post_processors.py
experiment_lab/experiments/monte_carlo/components/sample_filters.py
experiment_lab/experiments/monte_carlo/components/samplers.py
experiment_lab/experiments/rl/__init__.py
experiment_lab/experiments/rl/analysis.py
experiment_lab/experiments/rl/config.py
experiment_lab/experiments/rl/environment.py
experiment_lab/experiments/rl/experiment.py
experiment_lab-1.1.8.dist-info/LICENCE
experiment_lab-1.1.8.dist-info/METADATA
experiment_lab-1.1.8.dist-info/WHEEL
experiment_lab-1.1.8.dist-info/entry_points.txt
experiment_lab-1.1.8.dist-info/top_level.txt
experiment_lab-1.1.8.dist-info/RECORD
