Metadata-Version: 2.1
Name: experiment-lab
Version: 1.1.8
Summary: A suite of flexible experiments of a variety of different tasks.
Author-email: Rishav Bhagat <rishavbhagat.cs@gmail.com>
Project-URL: Repository, https://github.com/rishavb123/ExperimentLab
Keywords: experiment,suite,lab
Requires-Python: >=3.11
License-File: LICENCE
Requires-Dist: hydra-core
Requires-Dist: numpy
Requires-Dist: pandas
Requires-Dist: torch
Requires-Dist: wandb
Requires-Dist: tensorboard
Requires-Dist: tqdm
Provides-Extra: all
Requires-Dist: gymnasium ; extra == 'all'
Requires-Dist: stable-baselines3 ; extra == 'all'
Requires-Dist: moviepy ; extra == 'all'
Requires-Dist: torchvision ; extra == 'all'
Requires-Dist: minigrid ; extra == 'all'
Provides-Extra: dev
Requires-Dist: pytest ; extra == 'dev'
Requires-Dist: black ; extra == 'dev'
Requires-Dist: build ; extra == 'dev'
Requires-Dist: twine ; extra == 'dev'
Provides-Extra: ml
Requires-Dist: torchvision ; extra == 'ml'
Provides-Extra: rl
Requires-Dist: gymnasium ; extra == 'rl'
Requires-Dist: stable-baselines3 ; extra == 'rl'
Requires-Dist: minigrid ; extra == 'rl'
Provides-Extra: rl-vid
Requires-Dist: moviepy ; extra == 'rl-vid'
